nodekit/.DS_Store
nodekit/__init__.py
nodekit/_internal/__init__.py
nodekit/_internal/ops/__init__.py
nodekit/_internal/ops/build_site/__init__.py
nodekit/_internal/ops/build_site/harness.j2
nodekit/_internal/ops/build_site/types.py
nodekit/_internal/ops/concat.py
nodekit/_internal/ops/open_asset_save_asset.py
nodekit/_internal/ops/play/__init__.py
nodekit/_internal/ops/play/local_runner/__init__.py
nodekit/_internal/ops/play/local_runner/main.py
nodekit/_internal/ops/play/local_runner/site-template.j2
nodekit/_internal/ops/save_graph_load_graph.py
nodekit/_internal/ops/simulate/__init__.py
nodekit/_internal/ops/simulate/evaluate_expression.py
nodekit/_internal/ops/simulate/sample_action.py
nodekit/_internal/ops/simulate/simulate.py
nodekit/_internal/ops/simulate/validate_action.py
nodekit/_internal/ops/topological_sorting.py
nodekit/_internal/types/__init__.py
nodekit/_internal/types/actions.py
nodekit/_internal/types/agents.py
nodekit/_internal/types/assets.py
nodekit/_internal/types/cards.py
nodekit/_internal/types/events.py
nodekit/_internal/types/expressions.py
nodekit/_internal/types/graph.py
nodekit/_internal/types/node.py
nodekit/_internal/types/sensors.py
nodekit/_internal/types/trace.py
nodekit/_internal/types/transitions.py
nodekit/_internal/types/values.py
nodekit/_internal/utils/__init__.py
nodekit/_internal/utils/get_browser_bundle.py
nodekit/_internal/utils/get_extension_from_media_type.py
nodekit/_internal/utils/hashing.py
nodekit/_internal/utils/iter_assets.py
nodekit/_internal/version.py
nodekit/_static/nodekit.css
nodekit/_static/nodekit.js
nodekit/actions.py
nodekit/agents.py
nodekit/assets.py
nodekit/cards.py
nodekit/events.py
nodekit/experimental/__init__.py
nodekit/experimental/s3.py
nodekit/experimental/turk/__init__.py
nodekit/experimental/turk/helper.py
nodekit/experimental/turk/models.py
nodekit/experimental/visualization/__init__.py
nodekit/experimental/visualization/pointer.py
nodekit/expressions.py
nodekit/sensors.py
nodekit-0.2.3.dist-info/WHEEL
nodekit-0.2.3.dist-info/METADATA
nodekit-0.2.3.dist-info/RECORD
