Metadata-Version: 2.3
Name: nodekit
Version: 0.2.3
Author: Michael J. Lee
Author-email: Michael J. Lee <mil@mit.edu>
License:                                  Apache License
Requires-Dist: pillow>=10.4
Requires-Dist: pydantic>=2.9.2
Requires-Dist: jinja2>=3.1.4
Requires-Dist: fastapi[standard]>=0.116.1
Requires-Dist: boto3>=1.40.55
Requires-Dist: matplotlib>=3.10.8
Requires-Dist: boto3-stubs~=1.42.10
Requires-Dist: pandas>=2.3.3
Requires-Python: >=3.12
Project-URL: repository, https://github.com/intelligence-observatory/nodekit
